enumchoicefield/__init__.py
enumchoicefield/admin.py
enumchoicefield/enum.py
enumchoicefield/fields.py
enumchoicefield/forms.py
enumchoicefield/utils.py
enumchoicefield/version.py
enumchoicefield/locale/de/LC_MESSAGES/django.mo
enumchoicefield/locale/de/LC_MESSAGES/django.po
enumchoicefield/tests/__init__.py
enumchoicefield/tests/models.py
enumchoicefield/tests/settings.py
enumchoicefield/tests/test_enum.py
enumchoicefield/tests/test_field.py
enumchoicefield/tests/test_forms.py
enumchoicefield/tests/test_utils.py
enumchoicefield/tests/locale/de/LC_MESSAGES/django.mo
enumchoicefield/tests/locale/de/LC_MESSAGES/django.po
enumchoicefield/tests/locale/en/LC_MESSAGES/django.mo
enumchoicefield/tests/locale/en/LC_MESSAGES/django.po
enumchoicefield/tests/migrations/0001_initial.py
enumchoicefield/tests/migrations/0002_make_nullable.py
enumchoicefield/tests/migrations/__init__.py
django_enumchoicefield-3.0.0.dist-info/LICENSE
django_enumchoicefield-3.0.0.dist-info/METADATA
django_enumchoicefield-3.0.0.dist-info/WHEEL
django_enumchoicefield-3.0.0.dist-info/top_level.txt
django_enumchoicefield-3.0.0.dist-info/RECORD
