Metadata-Version: 2.1
Name: django-enumchoicefield
Version: 3.0.0
Summary: A choice field for Django using native Python Enums
Home-page: https://github.com/timheap/django-enumchoicefield
Author: Tim Heap
Author-email: tim@timheap.me
License: BSD License
Platform: UNKNOWN
Classifier: Environment :: Web Environment
Classifier: Intended Audience :: Developers
Classifier: Operating System :: OS Independent
Classifier: Programming Language :: Python
Classifier: Programming Language :: Python :: 3
Classifier: Programming Language :: Python :: 3.5
Classifier: Programming Language :: Python :: 3.6
Classifier: Programming Language :: Python :: 3.7
Classifier: Programming Language :: Python :: 3.8
Classifier: Framework :: Django
Classifier: License :: OSI Approved :: BSD License
License-File: LICENSE
Requires-Dist: Django (>=2.0)
